Workbook
Name Aporte: ControleDeInvestimento_DIO!$D$28
Name Patrimonio: ControleDeInvestimento_DIO!$D$31
Name qtd_anos: ControleDeInvestimento_DIO!$D$29
Name Rendimento_Carteira: ControleDeInvestimento_DIO!$D$23
Name Salario: ControleDeInvestimento_DIO!$D$22
Name sugestao_investimento: ControleDeInvestimento_DIO!$D$24
Name taxa_mensal: ControleDeInvestimento_DIO!$D$30

Sheet ControleDeInvestimento_DIO
B21: CONFIGURAÇÕES
B22: Salario | D22: 2000
B23: Rendimento da Carteira | D23: 0.006
B24: Sugestão de Investimento | D24: =D22*30% -> 600
B27: INVESTIMENTO MENSAL
B28: Quanto Investir por Mês? | D28: 200
B29: Por Quantos Anos? | D29: 10
B30: Taxa de Rendimento Mensal? | D30: 0.0108
B31: Patrimonio Acumulado? | D31: =FV(taxa_mensal,qtd_anos*12,Aporte*-1) -> 48691.533
B32: Dividendos Mensais? | D32: =Patrimonio*Rendimento_Carteira -> 292.1492
B34: Cenários | D34: Dividendo
A35: 2 | B35: Quanto em 2 Anos? | C35: =FV($D$30,$A35*12,$D$28*-1) -> 5446.1727 | D35: =C35*Rendimento_Carteira -> 32.677036
A36: 5 | B36: Quanto em 5 Anos? | C36: =FV($D$30,$A36*12,$D$28*-1) -> 16760.804 | D36: =C36*Rendimento_Carteira -> 100.56482
A37: 10 | B37: Quanto em 10 Anos? | C37: =FV($D$30,$A37*12,$D$28*-1) -> 48691.533 | D37: =C37*Rendimento_Carteira -> 292.1492
A38: 20 | B38: Quanto em 20 Anos? | C38: =FV($D$30,$A38*12,$D$28*-1) -> 225409.8 | D38: =C38*Rendimento_Carteira -> 1352.4588
A39: 30 | B39: Quanto em 30 Anos? | C39: =FV($D$30,$A39*12,$D$28*-1) -> 866780.96 | D39: =C39*Rendimento_Carteira -> 5200.6858
B42: Perfil | C42: AGRESSIVO
B43: VALOR A SER INVESTIDO POR MÊS | C43: =Aporte -> 200
B45: TIPO DE FII | C45: Percentual Sugerido | D45: Valores
B46: PAPEL | C46: =VLOOKUP($C$42&"-"&B46,Planilha_Auxiliar_DIO!$A:$D,4,FALSE) -> 0.5 | D46: =C46*$C$43 -> 100
B47: TIJOLO | C47: =VLOOKUP($C$42&"-"&B47,Planilha_Auxiliar_DIO!$A:$D,4,FALSE) -> 0.1 | D47: =C47*$C$43 -> 20
B48: HIBRIDOS | C48: =VLOOKUP($C$42&"-"&B48,Planilha_Auxiliar_DIO!$A:$D,4,FALSE) -> 0.05 | D48: =C48*$C$43 -> 10
B49: FOFs | C49: =VLOOKUP($C$42&"-"&B49,Planilha_Auxiliar_DIO!$A:$D,4,FALSE) -> 0.05 | D49: =C49*$C$43 -> 10
B50: DESENVOLVIMENTO | C50: =VLOOKUP($C$42&"-"&B50,Planilha_Auxiliar_DIO!$A:$D,4,FALSE) -> 0.2 | D50: =C50*$C$43 -> 40
B51: HOTELARIAS | C51: =VLOOKUP($C$42&"-"&B51,Planilha_Auxiliar_DIO!$A:$D,4,FALSE) -> 0.1 | D51: =C51*$C$43 -> 20
B52: TOTAL | D52: =SUM(D46:D51) -> 200

Sheet Planilha_Auxiliar_DIO
A2: CHAVE | B2: PERFIL | C2: TIPO DE FII | D2: %
A3: =B3&"-"&C3 -> CONSERVADOR-PAPEL | B3: CONSERVADOR | C3: PAPEL | D3: 0.3
A4: =B4&"-"&C4 -> CONSERVADOR-TIJOLO | B4: CONSERVADOR | C4: TIJOLO | D4: 0.5
A5: =B5&"-"&C5 -> CONSERVADOR-HIBRIDOS | B5: CONSERVADOR | C5: HIBRIDOS | D5: 0.1
A6: =B6&"-"&C6 -> CONSERVADOR-FOFs | B6: CONSERVADOR | C6: FOFs | D6: 0.1
A7: =B7&"-"&C7 -> CONSERVADOR-DESENVOLVIMENTO | B7: CONSERVADOR | C7: DESENVOLVIMENTO | D7: 0
A8: =B8&"-"&C8 -> CONSERVADOR-HOTELARIAS | B8: CONSERVADOR | C8: HOTELARIAS | D8: 0
A9: =B9&"-"&C9 -> MODERADO-PAPEL | B9: MODERADO | C9: PAPEL | D9: 0.32
A10: =B10&"-"&C10 -> MODERADO-TIJOLO | B10: MODERADO | C10: TIJOLO | D10: 0.35
A11: =B11&"-"&C11 -> MODERADO-HIBRIDOS | B11: MODERADO | C11: HIBRIDOS | D11: 0.08
A12: =B12&"-"&C12 -> MODERADO-FOFs | B12: MODERADO | C12: FOFs | D12: 0.05
A13: =B13&"-"&C13 -> MODERADO-DESENVOLVIMENTO | B13: MODERADO | C13: DESENVOLVIMENTO | D13: 0.1
A14: =B14&"-"&C14 -> MODERADO-HOTELARIAS | B14: MODERADO | C14: HOTELARIAS | D14: 0.1
... A20: =B20&"-"&C20 -> AGRESSIVO-HOTELARIAS | B20: AGRESSIVO | C20: HOTELARIAS | D20: 0.1
